Workbook

Sheet Inputs
A1: Financial model assumptions
A2: Start Date | B2: 45688
A3: Revenue Growth | B3: 0.045
A4: Gross Margin | B4: 0.62
A5: Fixed Costs | B5: 12000
A6: Tax Rate | B6: 0.24
A7: Discount Rate | B7: 0.1
A8: Target Category | B8: Enterprise
A9: Target Region | B9: West
A12: Record | B12: Category | C12: Units | D12: Price | E12: Launch Date | F12: Region
A13: 1 | B13: Enterprise | C13: 20 | D13: 125.25 | E13: 45658 | F13: West
A14: 2 | B14: SMB | C14: 27 | D14: 138.25 | E14: 45689 | F14: East
A15: 3 | B15: Consumer | C15: 34 | D15: 151.25 | E15: 45717 | F15: South
A16: 4 | B16: Enterprise | C16: 41 | D16: 164.25 | E16: 45748 | F16: North
A17: 5 | B17: SMB | C17: 48 | D17: 177.25 | E17: 45778 | F17: West
A18: 6 | B18: Enterprise | C18: 20 | D18: 190.25 | E18: 45809 | F18: East
A19: 7 | B19: SMB | C19: 27 | D19: 203.25 | E19: 45839 | F19: South
A20: 8 | B20: Consumer | C20: 34 | D20: 216.25 | E20: 45870 | F20: North
A21: 9 | B21: Enterprise | C21: 41 | D21: 229.25 | E21: 45901 | F21: West
A22: 10 | B22: SMB | C22: 48 | D22: 242.25 | E22: 45931 | F22: East
A23: 11 | B23: Enterprise | C23: 20 | D23: 255.25 | E23: 45962 | F23: South
A24: 12 | B24: SMB | C24: 27 | D24: 268.25 | E24: 45992 | F24: North
... A52: 40 | B52: SMB | C52: 48 | D52: 292.25 | E52: 45748 | F52: North

Sheet Schedule
A1: Metric | B1: 1 | C1: 2 | D1: 3 | E1: 4 | F1: 5 | G1: 6 | H1: 7 | I1: 8 | J1: 9 | K1: 10 | L1: 11 | M1: 12
A2: Revenue | B2: =100000*(1+Inputs!$B$3)^(B$1-1) -> 100000 | C2: =100000*(1+Inputs!$B$3)^(C$1-1) -> 104500 | D2: =100000*(1+Inputs!$B$3)^(D$1-1) -> 109202.5 | E2: =100000*(1+Inputs!$B$3)^(E$1-1) -> 114116.61 | F2: =100000*(1+Inputs!$B$3)^(F$1-1) -> 119251.86 | G2: =100000*(1+Inputs!$B$3)^(G$1-1) -> 124618.19 | H2: =100000*(1+Inputs!$B$3)^(H$1-1) -> 130226.01 | I2: =100000*(1+Inputs!$B$3)^(I$1-1) -> 136086.18 | ... M2: =100000*(1+Inputs!$B$3)^(M$1-1) -> 162285.3
A3: Cost of Goods Sold | B3: =B2*(1-Inputs!$B$4) -> 38000 | C3: =C2*(1-Inputs!$B$4) -> 39710 | D3: =D2*(1-Inputs!$B$4) -> 41496.95 | E3: =E2*(1-Inputs!$B$4) -> 43364.313 | F3: =F2*(1-Inputs!$B$4) -> 45315.707 | G3: =G2*(1-Inputs!$B$4) -> 47354.914 | H3: =H2*(1-Inputs!$B$4) -> 49485.885 | I3: =I2*(1-Inputs!$B$4) -> 51712.75 | ... M3: =M2*(1-Inputs!$B$4) -> 61668.416
A4: Gross Profit | B4: =B2-B3 -> 62000 | C4: =C2-C3 -> 64790 | D4: =D2-D3 -> 67705.55 | E4: =E2-E3 -> 70752.3 | F4: =F2-F3 -> 73936.153 | G4: =G2-G3 -> 77263.28 | H4: =H2-H3 -> 80740.128 | I4: =I2-I3 -> 84373.433 | ... M4: =M2-M3 -> 100616.89
A5: Fixed Costs | B5: =Inputs!$B$5 -> 12000 | C5: =Inputs!$B$5 -> 12000 | D5: =Inputs!$B$5 -> 12000 | E5: =Inputs!$B$5 -> 12000 | F5: =Inputs!$B$5 -> 12000 | G5: =Inputs!$B$5 -> 12000 | H5: =Inputs!$B$5 -> 12000 | I5: =Inputs!$B$5 -> 12000 | ... M5: =Inputs!$B$5 -> 12000
A6: Target Units | B6: =SUMIF(Inputs!$B$13:$B$52,Inputs!$B$8,Inputs!$C$13:$C$52) -> 488 | C6: =SUMIF(Inputs!$B$13:$B$52,Inputs!$B$8,Inputs!$C$13:$C$52) -> 488 | D6: =SUMIF(Inputs!$B$13:$B$52,Inputs!$B$8,Inputs!$C$13:$C$52) -> 488 | E6: =SUMIF(Inputs!$B$13:$B$52,Inputs!$B$8,Inputs!$C$13:$C$52) -> 488 | F6: =SUMIF(Inputs!$B$13:$B$52,Inputs!$B$8,Inputs!$C$13:$C$52) -> 488 | G6: =SUMIF(Inputs!$B$13:$B$52,Inputs!$B$8,Inputs!$C$13:$C$52) -> 488 | H6: =SUMIF(Inputs!$B$13:$B$52,Inputs!$B$8,Inputs!$C$13:$C$52) -> 488 | I6: =SUMIF(Inputs!$B$13:$B$52,Inputs!$B$8,Inputs!$C$13:$C$52) -> 488 | ... M6: =SUMIF(Inputs!$B$13:$B$52,Inputs!$B$8,Inputs!$C$13:$C$52) -> 488
A7: Target Regional Price | B7: =SUMIFS(Inputs!$D$13:$D$52,Inputs!$B$13:$B$52,Inputs!$B$8,Inputs!$F$13:$F$52,Inputs!$B$9) -> 719 | C7: =SUMIFS(Inputs!$D$13:$D$52,Inputs!$B$13:$B$52,Inputs!$B$8,Inputs!$F$13:$F$52,Inputs!$B$9) -> 719 | D7: =SUMIFS(Inputs!$D$13:$D$52,Inputs!$B$13:$B$52,Inputs!$B$8,Inputs!$F$13:$F$52,Inputs!$B$9) -> 719 | E7: =SUMIFS(Inputs!$D$13:$D$52,Inputs!$B$13:$B$52,Inputs!$B$8,Inputs!$F$13:$F$52,Inputs!$B$9) -> 719 | F7: =SUMIFS(Inputs!$D$13:$D$52,Inputs!$B$13:$B$52,Inputs!$B$8,Inputs!$F$13:$F$52,Inputs!$B$9) -> 719 | G7: =SUMIFS(Inputs!$D$13:$D$52,Inputs!$B$13:$B$52,Inputs!$B$8,Inputs!$F$13:$F$52,Inputs!$B$9) -> 719 | H7: =SUMIFS(Inputs!$D$13:$D$52,Inputs!$B$13:$B$52,Inputs!$B$8,Inputs!$F$13:$F$52,Inputs!$B$9) -> 719 | I7: =SUMIFS(Inputs!$D$13:$D$52,Inputs!$B$13:$B$52,Inputs!$B$8,Inputs!$F$13:$F$52,Inputs!$B$9) -> 719 | ... M7: =SUMIFS(Inputs!$D$13:$D$52,Inputs!$B$13:$B$52,Inputs!$B$8,Inputs!$F$13:$F$52,Inputs!$B$9) -> 719
A8: Operating Costs | B8: =B3+B5+B6*B7+SUM(0) -> 400872 | C8: =C3+C5+C6*C7+SUM(0) -> 402582 | D8: =D3+D5+D6*D7+SUM(0) -> 404368.95 | E8: =E3+E5+E6*E7+SUM(0) -> 406236.31 | F8: =F3+F5+F6*F7+SUM(0) -> 408187.71 | G8: =G3+G5+G6*G7+SUM(0) -> 410226.91 | H8: =H3+H5+H6*H7+SUM(0) -> 412357.88 | I8: =I3+I5+I6*I7+SUM(0) -> 414584.75 | ... M8: =M3+M5+M6*M7+SUM(0) -> 424540.42
A9: EBITDA | B9: =B2-B8 -> -300872 | C9: =C2-C8 -> -298082 | D9: =D2-D8 -> -295166.45 | E9: =E2-E8 -> -292119.7 | F9: =F2-F8 -> -288935.85 | G9: =G2-G8 -> -285608.72 | H9: =H2-H8 -> -282131.87 | I9: =I2-I8 -> -278498.57 | ... M9: =M2-M8 -> -262255.11
A10: Tax | B10: =IF(B9>0,B9*Inputs!$B$6,0) -> 0 | C10: =IF(C9>0,C9*Inputs!$B$6,0) -> 0 | D10: =IF(D9>0,D9*Inputs!$B$6,0) -> 0 | E10: =IF(E9>0,E9*Inputs!$B$6,0) -> 0 | F10: =IF(F9>0,F9*Inputs!$B$6,0) -> 0 | G10: =IF(G9>0,G9*Inputs!$B$6,0) -> 0 | H10: =IF(H9>0,H9*Inputs!$B$6,0) -> 0 | I10: =IF(I9>0,I9*Inputs!$B$6,0) -> 0 | ... M10: =IF(M9>0,M9*Inputs!$B$6,0) -> 0
A11: Cash Flow | B11: =B9-B10-B2*0.08 -> -308872 | C11: =C9-C10-C2*0.08 -> -306442 | D11: =D9-D10-D2*0.08 -> -303902.65 | E11: =E9-E10-E2*0.08 -> -301249.03 | F11: =F9-F10-F2*0.08 -> -298476 | G11: =G9-G10-G2*0.08 -> -295578.18 | H11: =H9-H10-H2*0.08 -> -292549.95 | I11: =I9-I10-I2*0.08 -> -289385.46 | ... M11: =M9-M10-M2*0.08 -> -275237.94

Sheet Summary
A1: Summary Metric | B1: Value
A2: Positive cash flow flag | B2: =IF(SUM(Schedule!B11:M11)>0,1,0) -> 0
A3: Growth tier | B3: =IF(Inputs!$B$3>=0.05,3,IF(Inputs!$B$3>=0.03,2,1)) -> 2
A4: Minimum EBITDA | B4: =MIN(Schedule!B9:M9) -> -300872
A5: Maximum EBITDA | B5: =MAX(Schedule!B9:M9) -> -262255.11
A6: Average cash flow | B6: =ROUND(AVERAGE(Schedule!B11:M11),2) -> -293283.86
A7: VLOOKUP enterprise units | B7: =VLOOKUP("Enterprise",Inputs!$B$13:$D$52,2,FALSE()) -> 20
A8: INDEX/MATCH enterprise price | B8: =INDEX(Inputs!$D$13:$D$52,MATCH("Enterprise",Inputs!$B$13:$B$52,0)) -> 125.25
A10: Net present value | B10: =NPV(Inputs!$B$7,Schedule!B11:M11) -> -2021215.2
A11: Internal rate of return | B11: =IRR(B18:N18) -> 0.21332738
A12: Date plus three months | B12: =EDATE(Inputs!$B$2,3) -> 45777
A13: Month end plus three months | B13: =EOMONTH(Inputs!$B$2,3) -> 45777
A14: Enterprise records | B14: =COUNTIF(Inputs!$B$13:$B$52,"Enterprise") -> 16
A15: Enterprise west records | B15: =COUNTIFS(Inputs!$B$13:$B$52,"Enterprise",Inputs!$F$13:$F$52,"West") -> 4
A17: Signed cash-flow series for IRR
B18: -100000 | C18: 16500 | D18: 18000 | E18: 20500 | F18: 23000 | G18: 25000 | H18: 27000 | I18: 29500 | J18: 31500 | K18: 34000 | L18: 36000 | M18: 38500 | N18: 41000
